BudapestMetroDisplay/VERSION
BudapestMetroDisplay/__init__.py
BudapestMetroDisplay/_version.py
BudapestMetroDisplay/aps_helpers.py
BudapestMetroDisplay/bkk_opendata.py
BudapestMetroDisplay/config.py
BudapestMetroDisplay/esphome.py
BudapestMetroDisplay/gui.py
BudapestMetroDisplay/led_control.py
BudapestMetroDisplay/log.py
BudapestMetroDisplay/main.py
BudapestMetroDisplay/stops.py
BudapestMetroDisplay/webserver.py
budapestmetrodisplay-1.1.1.dist-info/licenses/LICENSE
budapestmetrodisplay-1.1.1.dist-info/METADATA
budapestmetrodisplay-1.1.1.dist-info/WHEEL
budapestmetrodisplay-1.1.1.dist-info/entry_points.txt
budapestmetrodisplay-1.1.1.dist-info/top_level.txt
budapestmetrodisplay-1.1.1.dist-info/RECORD
