Metadata-Version: 2.4
Name: BudapestMetroDisplay
Version: 1.1.1
Summary: Background service for a BudapestMetroDisplay hardware LED display
Author: denes44
Maintainer: denes44
License: MIT License
Project-URL: Documentation, https://github.com/denes44/BudapestMetroDisplay/blob/main/software/README.md
Project-URL: Repository, https://github.com/denes44/BudapestMetroDisplay.git
Project-URL: Bug Tracker, https://github.com/denes44/BudapestMetroDisplay/issues
Project-URL: Changelog, https://github.com/denes44/BudapestMetroDisplay/blob/main/software/CHANGELOG.md
Classifier: Development Status :: 3 - Alpha
Classifier: Programming Language :: Python :: 3.11
Classifier: License :: OSI Approved :: MIT License
Classifier: Environment :: No Input/Output (Daemon)
Classifier: Intended Audience :: End Users/Desktop
Classifier: Natural Language :: English
Classifier: Operating System :: OS Independent
Classifier: Topic :: Artistic Software
Classifier: Topic :: Multimedia
Requires-Python: >=3.11
License-File: LICENSE
Requires-Dist: aioesphomeapi~=27.0.0
Requires-Dist: APScheduler~=3.10.1
Requires-Dist: Flask~=3.0.3
Requires-Dist: numpy~=2.1.1
Requires-Dist: pydantic~=2.9.2
Requires-Dist: pydantic-settings~=2.6.0
Requires-Dist: pydantic_core
Requires-Dist: pytest~=8.3.3
Requires-Dist: requests>=2.32.0
Requires-Dist: sacn~=1.10.0
Dynamic: license-file
